{
    "tts_script": [
        {
            "voice": "Intro_Voice",
            "text": "がっこうで　せんせいが　がくせいに　はなしています。てすとは　いつですか。"
        },
        {
            "break": "1s"
        },
        {
            "voice": "Female_1",
            "text": "みなさん、こんしゅうの　げつようびに　しゅくだいを　だしてください。"
        },
        {
            "break": "0.5s"
        },
        {
            "voice": "Female_1",
            "text": "わたしが　しゅくだいを　みて　つぎのひに　かえします。"
        },
        {
            "break": "0.5s"
        },
        {
            "voice": "Female_1",
            "text": "そして　しゅくだいを　かえした　つぎのひに　てすとです。よく　べんきょうしてくださいね。"
        },
        {
            "break": "1s"
        },
        {
            "voice": "Intro_Voice",
            "text": "てすとは　いつですか。"
        }
    ]
}